entieda/__init__.py
entieda/entieda.py
entieda/misc/__init__.py
entieda/misc/info.py
entieda-0.0.1.dist-info/LICENSE
entieda-0.0.1.dist-info/METADATA
entieda-0.0.1.dist-info/WHEEL
entieda-0.0.1.dist-info/top_level.txt
entieda-0.0.1.dist-info/RECORD
