Metadata-Version: 2.1
Name: entieda
Version: 0.0.1
Summary: I do not know!
Home-page: https://github.com/azainiz/entieda
Author: Ahmad Zaini Zahrandika
Author-email: izay2001@gmail.com
License: MIT
Classifier: Programming Language :: Python :: 3
Classifier: License :: OSI Approved :: MIT License
Classifier: Operating System :: OS Independent
Requires-Python: >=3.12
License-File: LICENSE
